fggs/__init__.py
fggs/conjunction.py
fggs/derivations.py
fggs/domains.py
fggs/factorize.py
fggs/factors.py
fggs/fggs.py
fggs/formats.py
fggs/multi.py
fggs/semirings.py
fggs/solve.py
fggs/sum_product.py
fggs/utils.py
fggs/viterbi.py
fggs-0.1.dist-info/LICENSE.md
fggs-0.1.dist-info/METADATA
fggs-0.1.dist-info/WHEEL
fggs-0.1.dist-info/top_level.txt
fggs-0.1.dist-info/RECORD
