Metadata-Version: 2.1
Name: fggs
Version: 0.1
Summary: Factor Graph Grammars in Python
Home-page: https://github.com/diprism/fggs
Author-email: David Chiang <dchiang@nd.edu>, Darcey Riley <darcey.riley@nd.edu>, Ken Sible <ksible@nd.edu>
License: Copyright (c) 2021 University of Notre Dame        
Project-URL: Homepage, https://github.com/diprism/fggs
Platform: UNKNOWN
Classifier: Programming Language :: Python :: 3
Classifier: License :: OSI Approved :: MIT License
Classifier: Operating System :: OS Independent
Classifier: Topic :: Scientific/Engineering :: Artificial Intelligence
Requires-Python: >=3.7
License-File: LICENSE.md
Requires-Dist: torch (>=1.8)
Requires-Dist: torch-semiring-einsum (>=1.1)
Requires-Dist: pydot
Requires-Dist: tqdm
